toy_crypto/__about__.py
toy_crypto/__init__.py
toy_crypto/birthday.py
toy_crypto/bit_utils.py
toy_crypto/ec.py
toy_crypto/nt.py
toy_crypto/py.typed
toy_crypto/rand.py
toy_crypto/redundent.py
toy_crypto/rsa.py
toy_crypto/sec_games.py
toy_crypto/sieve.py
toy_crypto/types.py
toy_crypto/utils.py
toy_crypto/vigenere.py
toy_crypto/wycheproof.py
toycrypto-0.6.1.dist-info/METADATA
toycrypto-0.6.1.dist-info/WHEEL
toycrypto-0.6.1.dist-info/licenses/LICENSE.txt
toycrypto-0.6.1.dist-info/RECORD
