Metadata-Version: 2.4
Name: toycrypto
Version: 0.6.1
Summary: Modules that can be used to illustrate and explore cryptographic concepts. This should never be used for security purposes.
Project-URL: Documentation, https://jpgoldberg.github.io/toy-crypto-math/
Project-URL: Issues, https://github.com/jpgoldberg/toy-crypto-math/issues
Project-URL: Source, https://github.com/jpgoldberg/toy-crypto-math
Project-URL: Changelog, https://github.com/jpgoldberg/toy-crypto-math/blob/main/CHANGELOG.md
Author-email: Jeffrey Goldberg <jeffrey@goldmark.org>
License-Expression: MIT
License-File: LICENSE.txt
Classifier: Development Status :: 3 - Alpha
Classifier: Intended Audience :: Developers
Classifier: Intended Audience :: Education
Classifier: License :: OSI Approved :: MIT License
Classifier: Operating System :: OS Independent
Classifier: Programming Language :: Python
Classifier: Programming Language :: Python :: 3.12
Classifier: Programming Language :: Python :: 3.13
Classifier: Programming Language :: Python :: Implementation :: CPython
Classifier: Programming Language :: Python :: Implementation :: PyPy
Classifier: Topic :: Scientific/Engineering :: Mathematics
Classifier: Topic :: Security :: Cryptography
Classifier: Typing :: Typed
Requires-Python: >=3.12
Requires-Dist: jsonref>=1.1.0
Requires-Dist: jsonschema>=4.25.0
Requires-Dist: primefac>=2.0.12
Requires-Dist: referencing>=0.36.2
Provides-Extra: c-deps
Requires-Dist: bitarray; extra == 'c-deps'
